pymt5adapter/__init__.py
pymt5adapter/const.py
pymt5adapter/context.py
pymt5adapter/core.py
pymt5adapter/event.py
pymt5adapter/helpers.py
pymt5adapter/log.py
pymt5adapter/oem.py
pymt5adapter/order.py
pymt5adapter/state.py
pymt5adapter/symbol.py
pymt5adapter/trade.py
pymt5adapter/types.py
pymt5adapter-0.4.4.dist-info/LICENSE
pymt5adapter-0.4.4.dist-info/METADATA
pymt5adapter-0.4.4.dist-info/WHEEL
pymt5adapter-0.4.4.dist-info/top_level.txt
pymt5adapter-0.4.4.dist-info/RECORD
