Metadata-Version: 2.1
Name: pymt5adapter
Version: 0.4.4
Summary: A drop in replacement wrapper for the MetaTrader5 package
Home-page: https://github.com/nicholishen/pymt5adapter
Author: nicholishen
Author-email: nicholishen@tutanota.com
License: MIT
Platform: UNKNOWN
Requires-Python: >=3.6
Requires-Dist: MetaTrader5 (==5.0.33)
